iuindycar/Orchestrator.py
iuindycar/__init__.py
iuindycar-0.0.8.dist-info/LICENSE
iuindycar-0.0.8.dist-info/METADATA
iuindycar-0.0.8.dist-info/WHEEL
iuindycar-0.0.8.dist-info/top_level.txt
iuindycar-0.0.8.dist-info/RECORD
