Metadata-Version: 2.1
Name: iuindycar
Version: 0.0.8
Summary: This package can be used to communicate with the stream processing kubernetes cluster
Home-page: https://github.com/DSC-SPIDAL/IndyCar
Author: Chathura Widanage
Author-email: chathurawidanage@gmail.com
License: UNKNOWN
Platform: UNKNOWN
Classifier: Programming Language :: Python :: 3
Classifier: License :: OSI Approved :: Apache Software License
Classifier: Operating System :: OS Independent
Requires-Python: >=3.6
Requires-Dist: kubernetes
Requires-Dist: paho-mqtt
